bmiviz.py
bmiviz-0.0.4.dist-info/METADATA
bmiviz-0.0.4.dist-info/WHEEL
bmiviz-0.0.4.dist-info/entry_points.txt
bmiviz-0.0.4.dist-info/top_level.txt
bmiviz-0.0.4.dist-info/RECORD
