Metadata-Version: 2.1
Name: bmiviz
Version: 0.0.4
Summary: A package for visualizing BMI trend of each country
Home-page: https://github.com/MDchor/BMI-visualisation
Author: shotaro yoshimura
Author-email: shotaro.yoshimura.mdchor@gmail.com
License: UNKNOWN
Project-URL: Bug Tracker, https://github.com/MDchor/BMI-visualisation
Platform: UNKNOWN
Classifier: Programming Language :: Python :: 3
Classifier: License :: OSI Approved :: MIT License
Classifier: Operating System :: OS Independent
Requires-Python: >=3.7
